{
  "id": "events",
  "type": "collection",
  "page_props": {
    "header": "Regional<br>Events",
    "header_expanded": "Page Props: Header Expanded",
    "text": "Up Next: Miami<br>January 31, 6:30 p.m. – 8:30 p.m.",
    "about": "Emory Explores the Future",
    "button_scroll": "Scroll to details",
    "about_before_scroll": "ABOUT THE CAMPAIGN",
    "img_src": "events_lede.jpg",
    "video_src": "videos/intro_video_v03.mp4",
    "video_poster": "videos/poster.jpg",
    "video_webm_src": "videos/intro_video_v03.webm",
    "text_play": "Begin\r\nyour\r\nexperience",
    "text_skip": "Skip video",
    "cta_button_new_tab": "true",
    "cta_button_text": "REGISTER NOW",
    "cta_button_link": "https://securelb.imodules.com/s/1705/21/interior.aspx?sid=1705&gid=3&pgid=16954&cid=25625",
    "vertical_header_line": "true",
    "custom_css": "#carouselContent > .section.gallery-carousel { padding-top: 160px !important; } .footer__cta a.link-button { display: none; } .section.component-intro-text { padding-top: 194px; } .footer__contact__links a { text-decoration: none; } .footer__contact__heading { margin-bottom: 20px; } @media (max-width: 767.98px) { .section.component-intro-text { padding-top: 60px; } .section.gallery-carousel { padding-top: 100px !important; } } .section.component-intro-text .body-container { padding-top: 15px; } .section.component-intro-text .body-container .col-md-8.image-container { margin-bottom: 20px; } .section.component-bottom-navigation { display: none; }",
    "footer": {
      "cta_contact_info": {
        "big_title": "CONTACT INFORMATION",
        "heading": "Advancement Events",
        "email": "advancementevents@emory.edu",
        "hide_contact_information": "true",
        "hide_cta_button": "true"
      }
    }
  },
  "path": "events",
  "metatag": {
    "title": "Events - Emory 2036",
    "description": "",
    "image": "og_image.jpg",
    "robots": "noindex,nofollow"
  },
  "components": [
    {
      "component": "SectionIntro",
      "props": {
        "header": "We’re bringing our vision of the future on the road! Attend one of our regional events to learn how 2O36 is making a difference for Emory, your city, and the world.",
        "background_image": "about_isolated_bg_darker.png",
        "text": "<p>Enjoy an unforgettable evening of food, libations, connection, and inspiration with local Emory alumni, parents, and friends. Hear from a diverse panel of Emory leaders as they share the progress 2O36 is making for students and our shared future. You’ll come away with exclusive insight into the campaign’s signature themes, including student flourishing, A.I. humanity, cancer, and brain health.</p> <p>Regional events are free to attend, but registration is required using the links below.* Business or cocktail attire is recommended.</p>",
        "img_src": "events_section_intro.jpg",
        "media_src": "https://vimeo.com/videos/744364283/c02961400c",
        "media_alt": "SectionIntro 'media_alt' Duis rutrum, nisiac posuere rutrum, elit odio faucibus dui.",
        "media_type": "video"
      }
    },
    {
      "component": "GalleryCarousel",
      "props": {
        "title": "Past Event Photos",
        "slides": [
          {
            "component": "Teaser",
            "props": {
              "img_src": "2036Regional_Seoul_Selects-1.jpg",
              "media_src": "2036Regional_Seoul_Selects-1.jpg",
              "media_type": "image",
              "type": "gallery",
              "event_location": "Seoul",
              "event_date": "11/14/22",
              "slides": [
                {
                  "img_src": "2036Regional_Seoul_Selects-1.jpg",
                  "media_src": "2036Regional_Seoul_Selects-1.jpg",
                  "media_type": "image"
                },
                {
                  "img_src": "2036Regional_Seoul_Selects-27.jpg",
                  "media_src": "2036Regional_Seoul_Selects-27.jpg",
                  "media_type": "image"
                },
                {
                  "img_src": "2036Regional_Seoul_Selects-44.jpg",
                  "media_src": "2036Regional_Seoul_Selects-44.jpg",
                  "media_type": "image"
                },
                {
                  "img_src": "2036Regional_Seoul_Selects-61.jpg",
                  "media_src": "2036Regional_Seoul_Selects-61.jpg",
                  "media_type": "image"
                },
                {
                  "img_src": "2036Regional_Seoul_Selects-10.jpg",
                  "media_src": "2036Regional_Seoul_Selects-10.jpg",
                  "media_type": "image"
                },
                {
                  "img_src": "2036Regional_Seoul_Selects-28.jpg",
                  "media_src": "2036Regional_Seoul_Selects-28.jpg",
                  "media_type": "image"
                },
                {
                  "img_src": "2036Regional_Seoul_Selects-45.jpg",
                  "media_src": "2036Regional_Seoul_Selects-45.jpg",
                  "media_type": "image"
                },
                {
                  "img_src": "2036Regional_Seoul_Selects-62.jpg",
                  "media_src": "2036Regional_Seoul_Selects-62.jpg",
                  "media_type": "image"
                },
                {
                  "img_src": "2036Regional_Seoul_Selects-11.jpg",
                  "media_src": "2036Regional_Seoul_Selects-11.jpg",
                  "media_type": "image"
                },
                {
                  "img_src": "2036Regional_Seoul_Selects-29.jpg",
                  "media_src": "2036Regional_Seoul_Selects-29.jpg",
                  "media_type": "image"
                },
                {
                  "img_src": "2036Regional_Seoul_Selects-46.jpg",
                  "media_src": "2036Regional_Seoul_Selects-46.jpg",
                  "media_type": "image"
                },
                {
                  "img_src": "2036Regional_Seoul_Selects-63.jpg",
                  "media_src": "2036Regional_Seoul_Selects-63.jpg",
                  "media_type": "image"
                },
                {
                  "img_src": "2036Regional_Seoul_Selects-12.jpg",
                  "media_src": "2036Regional_Seoul_Selects-12.jpg",
                  "media_type": "image"
                },
                {
                  "img_src": "2036Regional_Seoul_Selects-3.jpg",
                  "media_src": "2036Regional_Seoul_Selects-3.jpg",
                  "media_type": "image"
                },
                {
                  "img_src": "2036Regional_Seoul_Selects-47.jpg",
                  "media_src": "2036Regional_Seoul_Selects-47.jpg",
                  "media_type": "image"
                },
                {
                  "img_src": "2036Regional_Seoul_Selects-64.jpg",
                  "media_src": "2036Regional_Seoul_Selects-64.jpg",
                  "media_type": "image"
                },
                {
                  "img_src": "2036Regional_Seoul_Selects-13.jpg",
                  "media_src": "2036Regional_Seoul_Selects-13.jpg",
                  "media_type": "image"
                },
                {
                  "img_src": "2036Regional_Seoul_Selects-30.jpg",
                  "media_src": "2036Regional_Seoul_Selects-30.jpg",
                  "media_type": "image"
                },
                {
                  "img_src": "2036Regional_Seoul_Selects-48.jpg",
                  "media_src": "2036Regional_Seoul_Selects-48.jpg",
                  "media_type": "image"
                },
                {
                  "img_src": "2036Regional_Seoul_Selects-65.jpg",
                  "media_src": "2036Regional_Seoul_Selects-65.jpg",
                  "media_type": "image"
                },
                {
                  "img_src": "2036Regional_Seoul_Selects-14.jpg",
                  "media_src": "2036Regional_Seoul_Selects-14.jpg",
                  "media_type": "image"
                },
                {
                  "img_src": "2036Regional_Seoul_Selects-31.jpg",
                  "media_src": "2036Regional_Seoul_Selects-31.jpg",
                  "media_type": "image"
                },
                {
                  "img_src": "2036Regional_Seoul_Selects-49.jpg",
                  "media_src": "2036Regional_Seoul_Selects-49.jpg",
                  "media_type": "image"
                },
                {
                  "img_src": "2036Regional_Seoul_Selects-66.jpg",
                  "media_src": "2036Regional_Seoul_Selects-66.jpg",
                  "media_type": "image"
                },
                {
                  "img_src": "2036Regional_Seoul_Selects-15.jpg",
                  "media_src": "2036Regional_Seoul_Selects-15.jpg",
                  "media_type": "image"
                },
                {
                  "img_src": "2036Regional_Seoul_Selects-32.jpg",
                  "media_src": "2036Regional_Seoul_Selects-32.jpg",
                  "media_type": "image"
                },
                {
                  "img_src": "2036Regional_Seoul_Selects-5.jpg",
                  "media_src": "2036Regional_Seoul_Selects-5.jpg",
                  "media_type": "image"
                },
                {
                  "img_src": "2036Regional_Seoul_Selects-67.jpg",
                  "media_src": "2036Regional_Seoul_Selects-67.jpg",
                  "media_type": "image"
                },
                {
                  "img_src": "2036Regional_Seoul_Selects-16.jpg",
                  "media_src": "2036Regional_Seoul_Selects-16.jpg",
                  "media_type": "image"
                },
                {
                  "img_src": "2036Regional_Seoul_Selects-33.jpg",
                  "media_src": "2036Regional_Seoul_Selects-33.jpg",
                  "media_type": "image"
                },
                {
                  "img_src": "2036Regional_Seoul_Selects-50.jpg",
                  "media_src": "2036Regional_Seoul_Selects-50.jpg",
                  "media_type": "image"
                },
                {
                  "img_src": "2036Regional_Seoul_Selects-68.jpg",
                  "media_src": "2036Regional_Seoul_Selects-68.jpg",
                  "media_type": "image"
                },
                {
                  "img_src": "2036Regional_Seoul_Selects-17.jpg",
                  "media_src": "2036Regional_Seoul_Selects-17.jpg",
                  "media_type": "image"
                },
                {
                  "img_src": "2036Regional_Seoul_Selects-34.jpg",
                  "media_src": "2036Regional_Seoul_Selects-34.jpg",
                  "media_type": "image"
                },
                {
                  "img_src": "2036Regional_Seoul_Selects-51.jpg",
                  "media_src": "2036Regional_Seoul_Selects-51.jpg",
                  "media_type": "image"
                },
                {
                  "img_src": "2036Regional_Seoul_Selects-69.jpg",
                  "media_src": "2036Regional_Seoul_Selects-69.jpg",
                  "media_type": "image"
                },
                {
                  "img_src": "2036Regional_Seoul_Selects-18.jpg",
                  "media_src": "2036Regional_Seoul_Selects-18.jpg",
                  "media_type": "image"
                },
                {
                  "img_src": "2036Regional_Seoul_Selects-35.jpg",
                  "media_src": "2036Regional_Seoul_Selects-35.jpg",
                  "media_type": "image"
                },
                {
                  "img_src": "2036Regional_Seoul_Selects-52.jpg",
                  "media_src": "2036Regional_Seoul_Selects-52.jpg",
                  "media_type": "image"
                },
                {
                  "img_src": "2036Regional_Seoul_Selects-7.jpg",
                  "media_src": "2036Regional_Seoul_Selects-7.jpg",
                  "media_type": "image"
                },
                {
                  "img_src": "2036Regional_Seoul_Selects-19.jpg",
                  "media_src": "2036Regional_Seoul_Selects-19.jpg",
                  "media_type": "image"
                },
                {
                  "img_src": "2036Regional_Seoul_Selects-36.jpg",
                  "media_src": "2036Regional_Seoul_Selects-36.jpg",
                  "media_type": "image"
                },
                {
                  "img_src": "2036Regional_Seoul_Selects-53.jpg",
                  "media_src": "2036Regional_Seoul_Selects-53.jpg",
                  "media_type": "image"
                },
                {
                  "img_src": "2036Regional_Seoul_Selects-70.jpg",
                  "media_src": "2036Regional_Seoul_Selects-70.jpg",
                  "media_type": "image"
                },
                {
                  "img_src": "2036Regional_Seoul_Selects-2.jpg",
                  "media_src": "2036Regional_Seoul_Selects-2.jpg",
                  "media_type": "image"
                },
                {
                  "img_src": "2036Regional_Seoul_Selects-37.jpg",
                  "media_src": "2036Regional_Seoul_Selects-37.jpg",
                  "media_type": "image"
                },
                {
                  "img_src": "2036Regional_Seoul_Selects-54.jpg",
                  "media_src": "2036Regional_Seoul_Selects-54.jpg",
                  "media_type": "image"
                },
                {
                  "img_src": "2036Regional_Seoul_Selects-71.jpg",
                  "media_src": "2036Regional_Seoul_Selects-71.jpg",
                  "media_type": "image"
                },
                {
                  "img_src": "2036Regional_Seoul_Selects-20.jpg",
                  "media_src": "2036Regional_Seoul_Selects-20.jpg",
                  "media_type": "image"
                },
                {
                  "img_src": "2036Regional_Seoul_Selects-38.jpg",
                  "media_src": "2036Regional_Seoul_Selects-38.jpg",
                  "media_type": "image"
                },
                {
                  "img_src": "2036Regional_Seoul_Selects-55.jpg",
                  "media_src": "2036Regional_Seoul_Selects-55.jpg",
                  "media_type": "image"
                },
                {
                  "img_src": "2036Regional_Seoul_Selects-72.jpg",
                  "media_src": "2036Regional_Seoul_Selects-72.jpg",
                  "media_type": "image"
                },
                {
                  "img_src": "2036Regional_Seoul_Selects-21.jpg",
                  "media_src": "2036Regional_Seoul_Selects-21.jpg",
                  "media_type": "image"
                },
                {
                  "img_src": "2036Regional_Seoul_Selects-39.jpg",
                  "media_src": "2036Regional_Seoul_Selects-39.jpg",
                  "media_type": "image"
                },
                {
                  "img_src": "2036Regional_Seoul_Selects-56.jpg",
                  "media_src": "2036Regional_Seoul_Selects-56.jpg",
                  "media_type": "image"
                },
                {
                  "img_src": "2036Regional_Seoul_Selects-73.jpg",
                  "media_src": "2036Regional_Seoul_Selects-73.jpg",
                  "media_type": "image"
                },
                {
                  "img_src": "2036Regional_Seoul_Selects-22.jpg",
                  "media_src": "2036Regional_Seoul_Selects-22.jpg",
                  "media_type": "image"
                },
                {
                  "img_src": "2036Regional_Seoul_Selects-4.jpg",
                  "media_src": "2036Regional_Seoul_Selects-4.jpg",
                  "media_type": "image"
                },
                {
                  "img_src": "2036Regional_Seoul_Selects-57.jpg",
                  "media_src": "2036Regional_Seoul_Selects-57.jpg",
                  "media_type": "image"
                },
                {
                  "img_src": "2036Regional_Seoul_Selects-74.jpg",
                  "media_src": "2036Regional_Seoul_Selects-74.jpg",
                  "media_type": "image"
                },
                {
                  "img_src": "2036Regional_Seoul_Selects-23.jpg",
                  "media_src": "2036Regional_Seoul_Selects-23.jpg",
                  "media_type": "image"
                },
                {
                  "img_src": "2036Regional_Seoul_Selects-40.jpg",
                  "media_src": "2036Regional_Seoul_Selects-40.jpg",
                  "media_type": "image"
                },
                {
                  "img_src": "2036Regional_Seoul_Selects-58.jpg",
                  "media_src": "2036Regional_Seoul_Selects-58.jpg",
                  "media_type": "image"
                },
                {
                  "img_src": "2036Regional_Seoul_Selects-80.jpg",
                  "media_src": "2036Regional_Seoul_Selects-80.jpg",
                  "media_type": "image"
                },
                {
                  "img_src": "2036Regional_Seoul_Selects-24.jpg",
                  "media_src": "2036Regional_Seoul_Selects-24.jpg",
                  "media_type": "image"
                },
                {
                  "img_src": "2036Regional_Seoul_Selects-41.jpg",
                  "media_src": "2036Regional_Seoul_Selects-41.jpg",
                  "media_type": "image"
                },
                {
                  "img_src": "2036Regional_Seoul_Selects-59.jpg",
                  "media_src": "2036Regional_Seoul_Selects-59.jpg",
                  "media_type": "image"
                },
                {
                  "img_src": "2036Regional_Seoul_Selects-90.jpg",
                  "media_src": "2036Regional_Seoul_Selects-90.jpg",
                  "media_type": "image"
                },
                {
                  "img_src": "2036Regional_Seoul_Selects-25.jpg",
                  "media_src": "2036Regional_Seoul_Selects-25.jpg",
                  "media_type": "image"
                },
                {
                  "img_src": "2036Regional_Seoul_Selects-42.jpg",
                  "media_src": "2036Regional_Seoul_Selects-42.jpg",
                  "media_type": "image"
                },
                {
                  "img_src": "2036Regional_Seoul_Selects-6.jpg",
                  "media_src": "2036Regional_Seoul_Selects-6.jpg",
                  "media_type": "image"
                },
                {
                  "img_src": "2036Regional_Seoul_Selects-26.jpg",
                  "media_src": "2036Regional_Seoul_Selects-26.jpg",
                  "media_type": "image"
                },
                {
                  "img_src": "2036Regional_Seoul_Selects-43.jpg",
                  "media_src": "2036Regional_Seoul_Selects-43.jpg",
                  "media_type": "image"
                },
                {
                  "img_src": "2036Regional_Seoul_Selects-60.jpg",
                  "media_src": "2036Regional_Seoul_Selects-60.jpg",
                  "media_type": "image"
                }
              ]
            }
          },
          {
            "component": "Teaser",
            "props": {
              "img_src": "249A0005.jpg",
              "media_src": "249A0005.jpg",
              "media_type": "image",
              "type": "gallery",
              "event_location": "Washington, DC",
              "event_date": "10/24/22",
              "slides": [
                {
                  "img_src": "249A0005.jpg",
                  "media_src": "249A0005.jpg",
                  "media_type": "image"
                },
                {
                  "img_src": "249A0084.jpg",
                  "media_src": "249A0084.jpg",
                  "media_type": "image"
                },
                {
                  "img_src": "249A0600.jpg",
                  "media_src": "249A0600.jpg",
                  "media_type": "image"
                },
                {
                  "img_src": "249A0729.jpg",
                  "media_src": "249A0729.jpg",
                  "media_type": "image"
                },
                {
                  "img_src": "249A0746.jpg",
                  "media_src": "249A0746.jpg",
                  "media_type": "image"
                },
                {
                  "img_src": "249A0780.jpg",
                  "media_src": "249A0780.jpg",
                  "media_type": "image"
                },
                {
                  "img_src": "249A0832.jpg",
                  "media_src": "249A0832.jpg",
                  "media_type": "image"
                },
                {
                  "img_src": "249A9917.jpg",
                  "media_src": "249A9917.jpg",
                  "media_type": "image"
                },
                {
                  "img_src": "249A9987.jpg",
                  "media_src": "249A9987.jpg",
                  "media_type": "image"
                },
                {
                  "img_src": "249A0020.jpg",
                  "media_src": "249A0020.jpg",
                  "media_type": "image"
                },
                {
                  "img_src": "249A0124.jpg",
                  "media_src": "249A0124.jpg",
                  "media_type": "image"
                },
                {
                  "img_src": "249A0640.jpg",
                  "media_src": "249A0640.jpg",
                  "media_type": "image"
                },
                {
                  "img_src": "249A0732.jpg",
                  "media_src": "249A0732.jpg",
                  "media_type": "image"
                },
                {
                  "img_src": "249A0750.jpg",
                  "media_src": "249A0750.jpg",
                  "media_type": "image"
                },
                {
                  "img_src": "249A0781.jpg",
                  "media_src": "249A0781.jpg",
                  "media_type": "image"
                },
                {
                  "img_src": "249A9808.jpg",
                  "media_src": "249A9808.jpg",
                  "media_type": "image"
                },
                {
                  "img_src": "249A9922.jpg",
                  "media_src": "249A9922.jpg",
                  "media_type": "image"
                },
                {
                  "img_src": "249A9991.jpg",
                  "media_src": "249A9991.jpg",
                  "media_type": "image"
                },
                {
                  "img_src": "249A0027.jpg",
                  "media_src": "249A0027.jpg",
                  "media_type": "image"
                },
                {
                  "img_src": "249A0351.jpg",
                  "media_src": "249A0351.jpg",
                  "media_type": "image"
                },
                {
                  "img_src": "249A0665.jpg",
                  "media_src": "249A0665.jpg",
                  "media_type": "image"
                },
                {
                  "img_src": "249A0735.jpg",
                  "media_src": "249A0735.jpg",
                  "media_type": "image"
                },
                {
                  "img_src": "249A0759.jpg",
                  "media_src": "249A0759.jpg",
                  "media_type": "image"
                },
                {
                  "img_src": "249A0783.jpg",
                  "media_src": "249A0783.jpg",
                  "media_type": "image"
                },
                {
                  "img_src": "249A9812.jpg",
                  "media_src": "249A9812.jpg",
                  "media_type": "image"
                },
                {
                  "img_src": "249A9928.jpg",
                  "media_src": "249A9928.jpg",
                  "media_type": "image"
                },
                {
                  "img_src": "249A9993.jpg",
                  "media_src": "249A9993.jpg",
                  "media_type": "image"
                },
                {
                  "img_src": "249A0030.jpg",
                  "media_src": "249A0030.jpg",
                  "media_type": "image"
                },
                {
                  "img_src": "249A0356.jpg",
                  "media_src": "249A0356.jpg",
                  "media_type": "image"
                },
                {
                  "img_src": "249A0693.jpg",
                  "media_src": "249A0693.jpg",
                  "media_type": "image"
                },
                {
                  "img_src": "249A0739.jpg",
                  "media_src": "249A0739.jpg",
                  "media_type": "image"
                },
                {
                  "img_src": "249A0771.jpg",
                  "media_src": "249A0771.jpg",
                  "media_type": "image"
                },
                {
                  "img_src": "249A0807.jpg",
                  "media_src": "249A0807.jpg",
                  "media_type": "image"
                },
                {
                  "img_src": "249A9836.jpg",
                  "media_src": "249A9836.jpg",
                  "media_type": "image"
                },
                {
                  "img_src": "249A9934.jpg",
                  "media_src": "249A9934.jpg",
                  "media_type": "image"
                },
                {
                  "img_src": "249A0050.jpg",
                  "media_src": "249A0050.jpg",
                  "media_type": "image"
                },
                {
                  "img_src": "249A0590.jpg",
                  "media_src": "249A0590.jpg",
                  "media_type": "image"
                },
                {
                  "img_src": "249A0709.jpg",
                  "media_src": "249A0709.jpg",
                  "media_type": "image"
                },
                {
                  "img_src": "249A0743.jpg",
                  "media_src": "249A0743.jpg",
                  "media_type": "image"
                },
                {
                  "img_src": "249A0772.jpg",
                  "media_src": "249A0772.jpg",
                  "media_type": "image"
                },
                {
                  "img_src": "249A0816.jpg",
                  "media_src": "249A0816.jpg",
                  "media_type": "image"
                },
                {
                  "img_src": "249A9896.jpg",
                  "media_src": "249A9896.jpg",
                  "media_type": "image"
                },
                {
                  "img_src": "249A9940.jpg",
                  "media_src": "249A9940.jpg",
                  "media_type": "image"
                },
                {
                  "img_src": "249A0081.jpg",
                  "media_src": "249A0081.jpg",
                  "media_type": "image"
                },
                {
                  "img_src": "249A0594.jpg",
                  "media_src": "249A0594.jpg",
                  "media_type": "image"
                },
                {
                  "img_src": "249A0725.jpg",
                  "media_src": "249A0725.jpg",
                  "media_type": "image"
                },
                {
                  "img_src": "249A0744.jpg",
                  "media_src": "249A0744.jpg",
                  "media_type": "image"
                },
                {
                  "img_src": "249A0777.jpg",
                  "media_src": "249A0777.jpg",
                  "media_type": "image"
                },
                {
                  "img_src": "249A0820.jpg",
                  "media_src": "249A0820.jpg",
                  "media_type": "image"
                },
                {
                  "img_src": "249A9898.jpg",
                  "media_src": "249A9898.jpg",
                  "media_type": "image"
                },
                {
                  "img_src": "249A9983.jpg",
                  "media_src": "249A9983.jpg",
                  "media_type": "image"
                }
              ]
            }
          },
          {
            "component": "Teaser",
            "props": {
              "img_src": "2036_Regional_AL_10.13.22__Z060866.jpg",
              "media_src": "2036_Regional_AL_10.13.22__Z060866.jpg",
              "media_type": "image",
              "type": "gallery",
              "event_location": "Birmingham",
              "event_date": "10/13/22",
              "slides": [
                {
                  "img_src": "2036_Regional_AL_10.13.22__Z060866.jpg",
                  "media_src": "2036_Regional_AL_10.13.22__Z060866.jpg",
                  "media_type": "image"
                },
                {
                  "img_src": "2036_Regional_AL_10.13.22__Z060886.jpg",
                  "media_src": "2036_Regional_AL_10.13.22__Z060886.jpg",
                  "media_type": "image"
                },
                {
                  "img_src": "2036_Regional_AL_10.13.22__Z060887.jpg",
                  "media_src": "2036_Regional_AL_10.13.22__Z060887.jpg",
                  "media_type": "image"
                },
                {
                  "img_src": "2036_Regional_AL_10.13.22__Z060892.jpg",
                  "media_src": "2036_Regional_AL_10.13.22__Z060892.jpg",
                  "media_type": "image"
                },
                {
                  "img_src": "2036_Regional_AL_10.13.22__Z060894.jpg",
                  "media_src": "2036_Regional_AL_10.13.22__Z060894.jpg",
                  "media_type": "image"
                },
                {
                  "img_src": "2036_Regional_AL_10.13.22__Z060906.jpg",
                  "media_src": "2036_Regional_AL_10.13.22__Z060906.jpg",
                  "media_type": "image"
                },
                {
                  "img_src": "2036_Regional_AL_10.13.22__Z060912.jpg",
                  "media_src": "2036_Regional_AL_10.13.22__Z060912.jpg",
                  "media_type": "image"
                },
                {
                  "img_src": "2036_Regional_AL_10.13.22__Z060916.jpg",
                  "media_src": "2036_Regional_AL_10.13.22__Z060916.jpg",
                  "media_type": "image"
                },
                {
                  "img_src": "2036_Regional_AL_10.13.22__Z060919.jpg",
                  "media_src": "2036_Regional_AL_10.13.22__Z060919.jpg",
                  "media_type": "image"
                },
                {
                  "img_src": "2036_Regional_AL_10.13.22__Z060921.jpg",
                  "media_src": "2036_Regional_AL_10.13.22__Z060921.jpg",
                  "media_type": "image"
                },
                {
                  "img_src": "2036_Regional_AL_10.13.22__Z060924.jpg",
                  "media_src": "2036_Regional_AL_10.13.22__Z060924.jpg",
                  "media_type": "image"
                },
                {
                  "img_src": "2036_Regional_AL_10.13.22__Z060927.jpg",
                  "media_src": "2036_Regional_AL_10.13.22__Z060927.jpg",
                  "media_type": "image"
                },
                {
                  "img_src": "2036_Regional_AL_10.13.22__Z060933.jpg",
                  "media_src": "2036_Regional_AL_10.13.22__Z060933.jpg",
                  "media_type": "image"
                },
                {
                  "img_src": "2036_Regional_AL_10.13.22__Z060937.jpg",
                  "media_src": "2036_Regional_AL_10.13.22__Z060937.jpg",
                  "media_type": "image"
                },
                {
                  "img_src": "2036_Regional_AL_10.13.22__Z060940.jpg",
                  "media_src": "2036_Regional_AL_10.13.22__Z060940.jpg",
                  "media_type": "image"
                },
                {
                  "img_src": "2036_Regional_AL_10.13.22__Z060941.jpg",
                  "media_src": "2036_Regional_AL_10.13.22__Z060941.jpg",
                  "media_type": "image"
                },
                {
                  "img_src": "2036_Regional_AL_10.13.22__Z060966.jpg",
                  "media_src": "2036_Regional_AL_10.13.22__Z060966.jpg",
                  "media_type": "image"
                },
                {
                  "img_src": "2036_Regional_AL_10.13.22__Z060987.jpg",
                  "media_src": "2036_Regional_AL_10.13.22__Z060987.jpg",
                  "media_type": "image"
                },
                {
                  "img_src": "2036_Regional_AL_10.13.22__Z060990.jpg",
                  "media_src": "2036_Regional_AL_10.13.22__Z060990.jpg",
                  "media_type": "image"
                },
                {
                  "img_src": "2036_Regional_AL_10.13.22__Z060994.jpg",
                  "media_src": "2036_Regional_AL_10.13.22__Z060994.jpg",
                  "media_type": "image"
                },
                {
                  "img_src": "2036_Regional_AL_10.13.22__Z060998.jpg",
                  "media_src": "2036_Regional_AL_10.13.22__Z060998.jpg",
                  "media_type": "image"
                },
                {
                  "img_src": "2036_Regional_AL_10.13.22__Z061002.jpg",
                  "media_src": "2036_Regional_AL_10.13.22__Z061002.jpg",
                  "media_type": "image"
                },
                {
                  "img_src": "2036_Regional_AL_10.13.22__Z061005.jpg",
                  "media_src": "2036_Regional_AL_10.13.22__Z061005.jpg",
                  "media_type": "image"
                },
                {
                  "img_src": "2036_Regional_AL_10.13.22__Z061008.jpg",
                  "media_src": "2036_Regional_AL_10.13.22__Z061008.jpg",
                  "media_type": "image"
                },
                {
                  "img_src": "2036_Regional_AL_10.13.22__Z061012.jpg",
                  "media_src": "2036_Regional_AL_10.13.22__Z061012.jpg",
                  "media_type": "image"
                },
                {
                  "img_src": "2036_Regional_AL_10.13.22__Z061015.jpg",
                  "media_src": "2036_Regional_AL_10.13.22__Z061015.jpg",
                  "media_type": "image"
                },
                {
                  "img_src": "2036_Regional_AL_10.13.22__Z061021.jpg",
                  "media_src": "2036_Regional_AL_10.13.22__Z061021.jpg",
                  "media_type": "image"
                },
                {
                  "img_src": "2036_Regional_AL_10.13.22__Z061025.jpg",
                  "media_src": "2036_Regional_AL_10.13.22__Z061025.jpg",
                  "media_type": "image"
                },
                {
                  "img_src": "2036_Regional_AL_10.13.22__Z061027.jpg",
                  "media_src": "2036_Regional_AL_10.13.22__Z061027.jpg",
                  "media_type": "image"
                },
                {
                  "img_src": "2036_Regional_AL_10.13.22__Z061035.jpg",
                  "media_src": "2036_Regional_AL_10.13.22__Z061035.jpg",
                  "media_type": "image"
                },
                {
                  "img_src": "2036_Regional_AL_10.13.22__Z061042.jpg",
                  "media_src": "2036_Regional_AL_10.13.22__Z061042.jpg",
                  "media_type": "image"
                },
                {
                  "img_src": "2036_Regional_AL_10.13.22__Z061044.jpg",
                  "media_src": "2036_Regional_AL_10.13.22__Z061044.jpg",
                  "media_type": "image"
                },
                {
                  "img_src": "2036_Regional_AL_10.13.22__Z061045.jpg",
                  "media_src": "2036_Regional_AL_10.13.22__Z061045.jpg",
                  "media_type": "image"
                },
                {
                  "img_src": "2036_Regional_AL_10.13.22__Z061050.jpg",
                  "media_src": "2036_Regional_AL_10.13.22__Z061050.jpg",
                  "media_type": "image"
                },
                {
                  "img_src": "2036_Regional_AL_10.13.22__Z061056.jpg",
                  "media_src": "2036_Regional_AL_10.13.22__Z061056.jpg",
                  "media_type": "image"
                },
                {
                  "img_src": "2036_Regional_AL_10.13.22__Z061110.jpg",
                  "media_src": "2036_Regional_AL_10.13.22__Z061110.jpg",
                  "media_type": "image"
                },
                {
                  "img_src": "2036_Regional_AL_10.13.22__Z061188.jpg",
                  "media_src": "2036_Regional_AL_10.13.22__Z061188.jpg",
                  "media_type": "image"
                },
                {
                  "img_src": "2036_Regional_AL_10.13.22__Z061195.jpg",
                  "media_src": "2036_Regional_AL_10.13.22__Z061195.jpg",
                  "media_type": "image"
                },
                {
                  "img_src": "2036_Regional_AL_10.13.22__Z061352.jpg",
                  "media_src": "2036_Regional_AL_10.13.22__Z061352.jpg",
                  "media_type": "image"
                },
                {
                  "img_src": "2036_Regional_AL_10.13.22__Z061370.jpg",
                  "media_src": "2036_Regional_AL_10.13.22__Z061370.jpg",
                  "media_type": "image"
                },
                {
                  "img_src": "2036_Regional_AL_10.13.22__Z061376.jpg",
                  "media_src": "2036_Regional_AL_10.13.22__Z061376.jpg",
                  "media_type": "image"
                },
                {
                  "img_src": "2036_Regional_AL_10.13.22__Z061448.jpg",
                  "media_src": "2036_Regional_AL_10.13.22__Z061448.jpg",
                  "media_type": "image"
                },
                {
                  "img_src": "2036_Regional_AL_10.13.22__Z061480.jpg",
                  "media_src": "2036_Regional_AL_10.13.22__Z061480.jpg",
                  "media_type": "image"
                },
                {
                  "img_src": "2036_Regional_AL_10.13.22__Z061553.jpg",
                  "media_src": "2036_Regional_AL_10.13.22__Z061553.jpg",
                  "media_type": "image"
                },
                {
                  "img_src": "2036_Regional_AL_10.13.22__Z061558.jpg",
                  "media_src": "2036_Regional_AL_10.13.22__Z061558.jpg",
                  "media_type": "image"
                },
                {
                  "img_src": "2036_Regional_AL_10.13.22__Z061576.jpg",
                  "media_src": "2036_Regional_AL_10.13.22__Z061576.jpg",
                  "media_type": "image"
                },
                {
                  "img_src": "2036_Regional_AL_10.13.22__Z061578.jpg",
                  "media_src": "2036_Regional_AL_10.13.22__Z061578.jpg",
                  "media_type": "image"
                },
                {
                  "img_src": "2036_Regional_AL_10.13.22__Z061581.jpg",
                  "media_src": "2036_Regional_AL_10.13.22__Z061581.jpg",
                  "media_type": "image"
                },
                {
                  "img_src": "2036_Regional_AL_10.13.22__Z061590.jpg",
                  "media_src": "2036_Regional_AL_10.13.22__Z061590.jpg",
                  "media_type": "image"
                },
                {
                  "img_src": "2036_Regional_AL_10.13.22__Z061603.jpg",
                  "media_src": "2036_Regional_AL_10.13.22__Z061603.jpg",
                  "media_type": "image"
                },
                {
                  "img_src": "2036_Regional_AL_10.13.22__Z061606.jpg",
                  "media_src": "2036_Regional_AL_10.13.22__Z061606.jpg",
                  "media_type": "image"
                },
                {
                  "img_src": "2036_Regional_AL_10.13.22__Z061618.jpg",
                  "media_src": "2036_Regional_AL_10.13.22__Z061618.jpg",
                  "media_type": "image"
                },
                {
                  "img_src": "2036_Regional_AL_10.13.22__Z061628.jpg",
                  "media_src": "2036_Regional_AL_10.13.22__Z061628.jpg",
                  "media_type": "image"
                },
                {
                  "img_src": "2036_Regional_AL_10.13.22__Z061633.jpg",
                  "media_src": "2036_Regional_AL_10.13.22__Z061633.jpg",
                  "media_type": "image"
                },
                {
                  "img_src": "2036_Regional_AL_10.13.22__Z061634.jpg",
                  "media_src": "2036_Regional_AL_10.13.22__Z061634.jpg",
                  "media_type": "image"
                },
                {
                  "img_src": "2036_Regional_AL_10.13.22__Z061644.jpg",
                  "media_src": "2036_Regional_AL_10.13.22__Z061644.jpg",
                  "media_type": "image"
                },
                {
                  "img_src": "2036_Regional_AL_10.13.22_birmingham-alabama-usa-2021-08-26-18-13-02-utc.jpg",
                  "media_src": "2036_Regional_AL_10.13.22_birmingham-alabama-usa-2021-08-26-18-13-02-utc.jpg",
                  "media_type": "image"
                },
                {
                  "img_src": "2036_Regional_AL_10.13.22_birmingham-alabama-usa-downtown-city-skyline-2021-09-03-22-27-29-utc.jpg",
                  "media_src": "2036_Regional_AL_10.13.22_birmingham-alabama-usa-downtown-city-skyline-2021-09-03-22-27-29-utc.jpg",
                  "media_type": "image"
                },
                {
                  "img_src": "_Z060721.jpg",
                  "media_src": "_Z060721.jpg",
                  "media_type": "image"
                },
                {
                  "img_src": "_Z060809.jpg",
                  "media_src": "_Z060809.jpg",
                  "media_type": "image"
                },
                {
                  "img_src": "_Z060862.jpg",
                  "media_src": "_Z060862.jpg",
                  "media_type": "image"
                },
                {
                  "img_src": "_Z060955.jpg",
                  "media_src": "_Z060955.jpg",
                  "media_type": "image"
                }
              ]
            }
          }
        ]
      }
    },
    {
      "component": "EventContainer",
      "props": {
        "header": "Upcoming Events",
        "subheader": "* All times listed are local",
        "items": [
          {
            "component": "Event",
            "props": {
              "title": "Miami",
              "date": "January 31",
              "time": "6:30 P.M. - 8:30 P.M.",
              "cta_button_link": "https://securelb.imodules.com/s/1705/21/interior.aspx?sid=1705&gid=3&pgid=16954&cid=25625",
              "cta_button_text": "REGISTER NOW",
              "cta_new_tab": true,
              "img_src": "events_student_flourishing.png",
              "img_title": "Student Flourishing",
              "img_subtitle": "EMORY EXPLORES THE FUTURE",
              "media_src": "events_student_flourishing.png",
              "media_alt": "asdf",
              "media_type": "image",
              "hide_icon": "true",
              "layout": "left"
            }
          },
          {
            "component": "Event",
            "props": {
              "title": "Boca Raton",
              "date": "February 8",
              "time": "6:30 P.M. - 8:30 P.M.",
              "cta_button_link": "https://securelb.imodules.com/s/1705/21/interior.aspx?sid=1705&gid=3&pgid=17080&cid=25792&bledit=1&dids=12334&appealcode=3VECE",
              "cta_button_text": "REGISTER NOW",
              "cta_new_tab": true,
              "img_src": "events_cancer.png",
              "img_title": "AI.Humanity",
              "img_subtitle": "EMORY EXPLORES THE FUTURE",
              "media_src": "events_cancer.png",
              "media_alt": "asdf",
              "media_type": "image",
              "hide_icon": "true",
              "layout": "right"
            }
          },
          {
            "component": "Event",
            "props": {
              "title": "Tampa",
              "date": "February 22",
              "time": "6:30 P.M. - 8:30 P.M.",
              "cta_button_link": "https://securelb.imodules.com/s/1705/21/interior.aspx?sid=1705&gid=3&pgid=17083&cid=25796&bledit=1&dids=3318&appealcode=3VEBH",
              "cta_button_text": "REGISTER NOW",
              "cta_new_tab": true,
              "img_src": "events_brain_health.png",
              "img_title": "Student Flourishing",
              "img_subtitle": "EMORY EXPLORES THE FUTURE",
              "media_src": "events_brain_health.png",
              "media_alt": "asdf",
              "media_type": "image",
              "hide_icon": "true",
              "layout": "left"
            }
          },
          {
            "component": "Event",
            "props": {
              "title": "Orlando",
              "date": "February 23",
              "time": "6:30 P.M. - 8:30 P.M.",
              "cta_button_link": "https://securelb.imodules.com/s/1705/21/interior.aspx?sid=1705&gid=3&pgid=17090&cid=25805&bledit=1&dids=3318&appealcode=3VEBH",
              "cta_button_text": "REGISTER NOW",
              "cta_new_tab": true,
              "img_src": "events_brain_health.png",
              "img_title": "AI.Humanity",
              "img_subtitle": "EMORY EXPLORES THE FUTURE",
              "media_src": "events_brain_health.png",
              "media_alt": "asdf",
              "media_type": "image",
              "hide_icon": "true",
              "layout": "right"
            }
          },
          {
            "component": "Event",
            "props": {
              "title": "New York City",
              "date": "March 3",
              "time": "6:30 P.M. - 8:30 P.M.",
              "cta_button_link": "https://securelb.imodules.com/s/1705/21/interior.aspx?sid=1705&gid=3&pgid=17102&cid=2582&bledit=1&dids=1004&appealcode=3VAIH",
              "cta_button_text": "REGISTER NOW",
              "cta_new_tab": true,
              "img_src": "events_ai.png",
              "img_title": "Student Flourishing",
              "img_subtitle": "EMORY EXPLORES THE FUTURE",
              "media_src": "events_ai.png",
              "media_alt": "asdf",
              "media_type": "image",
              "hide_icon": "true",
              "layout": "left"
            }
          },
          {
            "component": "Event",
            "props": {
              "title": "Houston",
              "date": "March 8",
              "time": "6:30 P.M. - 8:30 P.M.",
              "cta_button_link": "https://securelb.imodules.com/s/1705/21/interior.aspx?sid=1705&gid=3&pgid=17093&cid=25809&bledit=1&dids=7&appealcode=3VSFT",
              "cta_button_text": "REGISTER NOW",
              "cta_new_tab": true,
              "img_src": "events_student_flourishing.png",
              "img_title": "AI.Humanity",
              "img_subtitle": "EMORY EXPLORES THE FUTURE",
              "media_src": "events_student_flourishing.png",
              "media_alt": "asdf",
              "media_type": "image",
              "hide_icon": "true",
              "layout": "right"
            }
          },
          {
            "component": "Event",
            "props": {
              "title": "Dallas",
              "date": "March 9",
              "time": "6:30 P.M. - 8:30 P.M.",
              "cta_button_link": "https://www.engage.emory.edu/s/1705/21/interior.aspx?sid=1705&gid=3&pgid=17095&cid=25812&ecid=25812&crid=0&calpgid=13&calcid=1160",
              "cta_button_text": "REGISTER NOW",
              "cta_new_tab": true,
              "img_src": "events_student_flourishing.png",
              "img_title": "Student Flourishing",
              "img_subtitle": "EMORY EXPLORES THE FUTURE",
              "media_src": "events_student_flourishing.png",
              "media_alt": "asdf",
              "media_type": "image",
              "hide_icon": "true",
              "layout": "left"
            }
          },
          {
            "component": "Event",
            "props": {
              "title": "Los Angeles",
              "date": "April 10",
              "time": "6:30 P.M. - 8:30 P.M.",
              "cta_button_link": "https://securelb.imodules.com/s/1705/21/interior.aspx?sid=1705&gid=3&pgid=17105&cid=25825&bledit=1&dids=7&appealcode=3VSFT",
              "cta_button_text": "REGISTER NOW",
              "cta_new_tab": true,
              "img_src": "events_student_flourishing.png",
              "img_title": "AI.Humanity",
              "img_subtitle": "EMORY EXPLORES THE FUTURE",
              "media_src": "events_student_flourishing.png",
              "media_alt": "asdf",
              "media_type": "image",
              "hide_icon": "true",
              "layout": "right"
            }
          },
          {
            "component": "Event",
            "props": {
              "title": "Washington, DC",
              "date": "April 13",
              "time": "6:30 P.M. - 8:30 P.M.",
              "cta_button_link": "https://securelb.imodules.com/s/1705/21/interior.aspx?sid=1705&gid=3&pgid=17108&cid=25829&bledit=1&dids=7&appealcode=3VSFT",
              "cta_button_text": "REGISTER NOW",
              "cta_new_tab": true,
              "img_src": "events_cancer.png",
              "img_title": "Student Flourishing",
              "img_subtitle": "EMORY EXPLORES THE FUTURE",
              "media_src": "events_cancer.png",
              "media_alt": "asdf",
              "media_type": "image",
              "hide_icon": "true",
              "layout": "left"
            }
          },
          {
            "component": "Event",
            "props": {
              "title": "Boston",
              "date": "May 18",
              "time": "6:30 P.M. - 8:30 P.M.",
              "cta_button_link": "https://securelb.imodules.com/s/1705/21/interior.aspx?sid=1705&gid=3&pgid=17111&cid=25833&bledit=1&dids=7&appealcode=3VSFT",
              "cta_button_text": "REGISTER NOW",
              "cta_new_tab": true,
              "img_src": "events_student_flourishing.png",
              "img_title": "AI.Humanity",
              "img_subtitle": "EMORY EXPLORES THE FUTURE",
              "media_src": "events_student_flourishing.png",
              "media_alt": "asdf",
              "media_type": "image",
              "hide_icon": "true",
              "layout": "right"
            }
          }
        ]
      }
    }
  ]
}
